{
	"format": "BeepBox",
	"version": 6,
	"scale": "expert",
	"key": "A♯",
	"introBars": 0,
	"loopBars": 32,
	"beatsPerBar": 12,
	"ticksPerBeat": 8,
	"beatsPerMinute": 130,
	"reverb": 0,
	"channels": [
		{
			"type": "pitch",
			"octaveScrollBar": 3,
			"instruments": [
				{
					"type": "chip",
					"volume": 0,
					"wave": "square",
					"transition": "sudden",
					"filter": "bright",
					"chorus": "union",
					"effect": "none"
				}
			],
			"patterns": [
				{
					"instrument": 1,
					"notes": [
						{
							"pitches": [
								64
							],
							"points": [
								{
									"tick": 0,
									"pitchBend": 0,
									"volume": 100
								},
								{
									"tick": 2,
									"pitchBend": 0,
									"volume": 100
								}
							]
						},
						{
							"pitches": [
								62
							],
							"points": [
								{
									"tick": 2,
									"pitchBend": 0,
									"volume": 100
								},
								{
									"tick": 4,
									"pitchBend": 0,
									"volume": 100
								}
							]
						},
						{
							"pitches": [
								57
							],
							"points": [
								{
									"tick": 4,
									"pitchBend": 0,
									"volume": 100
								},
								{
									"tick": 6,
									"pitchBend": 0,
									"volume": 100
								}
							]
						},
						{
							"pitches": [
								52
							],
							"points": [
								{
									"tick": 6,
									"pitchBend": 0,
									"volume": 100
								},
								{
									"tick": 8,
									"pitchBend": 0,
									"volume": 100
								}
							]
						},
						{
							"pitches": [
								50
							],
							"points": [
								{
									"tick": 8,
									"pitchBend": 0,
									"volume": 100
								},
								{
									"tick": 10,
									"pitchBend": 0,
									"volume": 100
								}
							]
						},
						{
							"pitches": [
								45
							],
							"points": [
								{
									"tick": 10,
									"pitchBend": 0,
									"volume": 100
								},
								{
									"tick": 12,
									"pitchBend": 0,
									"volume": 100
								}
							]
						},
						{
							"pitches": [
								40
							],
							"points": [
								{
									"tick": 12,
									"pitchBend": 0,
									"volume": 100
								},
								{
									"tick": 32,
									"pitchBend": 0,
									"volume": 100
								}
							]
						}
					]
				},
				{
					"instrument": 1,
					"notes": []
				},
				{
					"instrument": 1,
					"notes": []
				},
				{
					"instrument": 1,
					"notes": []
				},
				{
					"instrument": 1,
					"notes": []
				},
				{
					"instrument": 1,
					"notes": []
				},
				{
					"instrument": 1,
					"notes": []
				},
				{
					"instrument": 1,
					"notes": []
				}
			],
			"sequence": [
				1,
				0,
				0,
				2,
				2,
				2,
				2,
				2,
				2,
				2,
				2,
				2,
				2,
				2,
				2,
				2,
				2,
				2,
				2,
				2,
				2,
				2,
				2,
				2,
				2,
				2,
				2,
				2,
				2,
				2,
				2,
				2
			]
		},
		{
			"type": "pitch",
			"octaveScrollBar": 2,
			"instruments": [
				{
					"type": "chip",
					"volume": 100,
					"wave": "square",
					"transition": "sudden",
					"filter": "bright",
					"chorus": "union",
					"effect": "none"
				}
			],
			"patterns": [
				{
					"instrument": 1,
					"notes": []
				},
				{
					"instrument": 1,
					"notes": []
				},
				{
					"instrument": 1,
					"notes": []
				},
				{
					"instrument": 1,
					"notes": []
				},
				{
					"instrument": 1,
					"notes": []
				},
				{
					"instrument": 1,
					"notes": []
				},
				{
					"instrument": 1,
					"notes": []
				},
				{
					"instrument": 1,
					"notes": []
				}
			],
			"sequence": [
				1,
				0,
				0,
				2,
				2,
				2,
				2,
				2,
				2,
				2,
				2,
				2,
				2,
				2,
				2,
				2,
				2,
				2,
				2,
				2,
				2,
				2,
				2,
				2,
				2,
				2,
				2,
				2,
				2,
				2,
				2,
				2
			]
		},
		{
			"type": "pitch",
			"octaveScrollBar": 2,
			"instruments": [
				{
					"type": "chip",
					"volume": 100,
					"wave": "square",
					"transition": "sudden",
					"filter": "bright",
					"chorus": "union",
					"effect": "none"
				}
			],
			"patterns": [
				{
					"instrument": 1,
					"notes": [
						{
							"pitches": [
								52
							],
							"points": [
								{
									"tick": 0,
									"pitchBend": 0,
									"volume": 100
								},
								{
									"tick": 2,
									"pitchBend": 0,
									"volume": 100
								}
							]
						},
						{
							"pitches": [
								50
							],
							"points": [
								{
									"tick": 2,
									"pitchBend": 0,
									"volume": 100
								},
								{
									"tick": 4,
									"pitchBend": 0,
									"volume": 100
								}
							]
						},
						{
							"pitches": [
								45
							],
							"points": [
								{
									"tick": 4,
									"pitchBend": 0,
									"volume": 100
								},
								{
									"tick": 6,
									"pitchBend": 0,
									"volume": 100
								}
							]
						},
						{
							"pitches": [
								40
							],
							"points": [
								{
									"tick": 6,
									"pitchBend": 0,
									"volume": 100
								},
								{
									"tick": 8,
									"pitchBend": 0,
									"volume": 100
								}
							]
						},
						{
							"pitches": [
								38
							],
							"points": [
								{
									"tick": 8,
									"pitchBend": 0,
									"volume": 100
								},
								{
									"tick": 10,
									"pitchBend": 0,
									"volume": 100
								}
							]
						},
						{
							"pitches": [
								33
							],
							"points": [
								{
									"tick": 10,
									"pitchBend": 0,
									"volume": 100
								},
								{
									"tick": 12,
									"pitchBend": 0,
									"volume": 100
								}
							]
						},
						{
							"pitches": [
								28
							],
							"points": [
								{
									"tick": 12,
									"pitchBend": 0,
									"volume": 100
								},
								{
									"tick": 32,
									"pitchBend": 0,
									"volume": 100
								}
							]
						}
					]
				},
				{
					"instrument": 1,
					"notes": [
						{
							"pitches": [
								40
							],
							"points": [
								{
									"tick": 0,
									"pitchBend": 0,
									"volume": 100
								},
								{
									"tick": 20,
									"pitchBend": 0,
									"volume": 100
								}
							]
						}
					]
				},
				{
					"instrument": 1,
					"notes": []
				},
				{
					"instrument": 1,
					"notes": []
				},
				{
					"instrument": 1,
					"notes": []
				},
				{
					"instrument": 1,
					"notes": []
				},
				{
					"instrument": 1,
					"notes": []
				},
				{
					"instrument": 1,
					"notes": []
				}
			],
			"sequence": [
				1,
				0,
				0,
				2,
				2,
				2,
				2,
				2,
				2,
				2,
				2,
				2,
				2,
				2,
				2,
				2,
				2,
				2,
				2,
				2,
				2,
				2,
				2,
				2,
				2,
				2,
				2,
				2,
				2,
				2,
				2,
				2
			]
		},
		{
			"type": "pitch",
			"octaveScrollBar": 2,
			"instruments": [
				{
					"type": "chip",
					"volume": 100,
					"wave": "square",
					"transition": "sudden",
					"filter": "bright",
					"chorus": "union",
					"effect": "none"
				}
			],
			"patterns": [
				{
					"instrument": 1,
					"notes": []
				},
				{
					"instrument": 1,
					"notes": []
				},
				{
					"instrument": 1,
					"notes": []
				},
				{
					"instrument": 1,
					"notes": []
				},
				{
					"instrument": 1,
					"notes": []
				},
				{
					"instrument": 1,
					"notes": []
				},
				{
					"instrument": 1,
					"notes": []
				},
				{
					"instrument": 1,
					"notes": []
				}
			],
			"sequence": [
				1,
				0,
				0,
				2,
				2,
				2,
				2,
				2,
				2,
				2,
				2,
				2,
				2,
				2,
				2,
				2,
				2,
				2,
				2,
				2,
				2,
				2,
				2,
				2,
				2,
				2,
				2,
				2,
				2,
				2,
				2,
				2
			]
		},
		{
			"type": "pitch",
			"octaveScrollBar": 3,
			"instruments": [
				{
					"type": "chip",
					"volume": 100,
					"wave": "square",
					"transition": "sudden",
					"filter": "bright",
					"chorus": "union",
					"effect": "none"
				}
			],
			"patterns": [
				{
					"instrument": 1,
					"notes": []
				},
				{
					"instrument": 1,
					"notes": []
				},
				{
					"instrument": 1,
					"notes": []
				},
				{
					"instrument": 1,
					"notes": []
				},
				{
					"instrument": 1,
					"notes": []
				},
				{
					"instrument": 1,
					"notes": []
				},
				{
					"instrument": 1,
					"notes": []
				},
				{
					"instrument": 1,
					"notes": []
				}
			],
			"sequence": [
				1,
				0,
				0,
				2,
				2,
				2,
				2,
				2,
				2,
				2,
				2,
				2,
				2,
				2,
				2,
				2,
				2,
				2,
				2,
				2,
				2,
				2,
				2,
				2,
				2,
				2,
				2,
				2,
				2,
				2,
				2,
				2
			]
		},
		{
			"type": "pitch",
			"octaveScrollBar": 2,
			"instruments": [
				{
					"type": "chip",
					"volume": 60,
					"wave": "square",
					"transition": "sudden",
					"filter": "bright",
					"chorus": "custom harmony",
					"effect": "none"
				}
			],
			"patterns": [
				{
					"instrument": 1,
					"notes": [
						{
							"pitches": [
								35,
								40
							],
							"points": [
								{
									"tick": 64,
									"pitchBend": 0,
									"volume": 100
								},
								{
									"tick": 96,
									"pitchBend": 0,
									"volume": 100
								}
							]
						}
					]
				},
				{
					"instrument": 1,
					"notes": [
						{
							"pitches": [
								42,
								37
							],
							"points": [
								{
									"tick": 0,
									"pitchBend": 0,
									"volume": 100
								},
								{
									"tick": 32,
									"pitchBend": 0,
									"volume": 100
								}
							]
						},
						{
							"pitches": [
								38,
								43
							],
							"points": [
								{
									"tick": 32,
									"pitchBend": 0,
									"volume": 100
								},
								{
									"tick": 64,
									"pitchBend": 0,
									"volume": 100
								}
							]
						},
						{
							"pitches": [
								45,
								40
							],
							"points": [
								{
									"tick": 64,
									"pitchBend": 0,
									"volume": 100
								},
								{
									"tick": 96,
									"pitchBend": 0,
									"volume": 100
								}
							]
						}
					]
				},
				{
					"instrument": 1,
					"notes": [
						{
							"pitches": [
								35,
								40
							],
							"points": [
								{
									"tick": 0,
									"pitchBend": 0,
									"volume": 100
								},
								{
									"tick": 32,
									"pitchBend": 0,
									"volume": 100
								}
							]
						},
						{
							"pitches": [
								42,
								37
							],
							"points": [
								{
									"tick": 32,
									"pitchBend": 0,
									"volume": 100
								},
								{
									"tick": 64,
									"pitchBend": 0,
									"volume": 100
								}
							]
						},
						{
							"pitches": [
								38,
								43
							],
							"points": [
								{
									"tick": 64,
									"pitchBend": 0,
									"volume": 100
								},
								{
									"tick": 96,
									"pitchBend": 0,
									"volume": 100
								}
							]
						}
					]
				},
				{
					"instrument": 1,
					"notes": [
						{
							"pitches": [
								45,
								40
							],
							"points": [
								{
									"tick": 0,
									"pitchBend": 0,
									"volume": 100
								},
								{
									"tick": 32,
									"pitchBend": 0,
									"volume": 100
								}
							]
						},
						{
							"pitches": [
								35,
								40
							],
							"points": [
								{
									"tick": 32,
									"pitchBend": 0,
									"volume": 100
								},
								{
									"tick": 64,
									"pitchBend": 0,
									"volume": 100
								}
							]
						},
						{
							"pitches": [
								42,
								37
							],
							"points": [
								{
									"tick": 64,
									"pitchBend": 0,
									"volume": 100
								},
								{
									"tick": 96,
									"pitchBend": 0,
									"volume": 100
								}
							]
						}
					]
				},
				{
					"instrument": 1,
					"notes": [
						{
							"pitches": [
								38,
								43
							],
							"points": [
								{
									"tick": 0,
									"pitchBend": 0,
									"volume": 100
								},
								{
									"tick": 32,
									"pitchBend": 0,
									"volume": 100
								}
							]
						},
						{
							"pitches": [
								40,
								45
							],
							"points": [
								{
									"tick": 32,
									"pitchBend": 0,
									"volume": 100
								},
								{
									"tick": 64,
									"pitchBend": 0,
									"volume": 100
								}
							]
						},
						{
							"pitches": [
								35,
								40
							],
							"points": [
								{
									"tick": 64,
									"pitchBend": 0,
									"volume": 100
								},
								{
									"tick": 96,
									"pitchBend": 0,
									"volume": 100
								}
							]
						}
					]
				},
				{
					"instrument": 1,
					"notes": []
				},
				{
					"instrument": 1,
					"notes": []
				},
				{
					"instrument": 1,
					"notes": [
						{
							"pitches": [
								38,
								43
							],
							"points": [
								{
									"tick": 0,
									"pitchBend": 0,
									"volume": 100
								},
								{
									"tick": 32,
									"pitchBend": 0,
									"volume": 100
								}
							]
						},
						{
							"pitches": [
								40,
								45
							],
							"points": [
								{
									"tick": 32,
									"pitchBend": 0,
									"volume": 100
								},
								{
									"tick": 52,
									"pitchBend": 0,
									"volume": 100
								}
							]
						},
						{
							"pitches": [
								35,
								40
							],
							"points": [
								{
									"tick": 64,
									"pitchBend": 0,
									"volume": 100
								},
								{
									"tick": 96,
									"pitchBend": 0,
									"volume": 100
								}
							]
						}
					]
				}
			],
			"sequence": [
				0,
				3,
				4,
				8,
				2,
				3,
				4,
				5,
				2,
				3,
				4,
				5,
				2,
				3,
				4,
				5,
				2,
				3,
				4,
				5,
				2,
				3,
				4,
				5,
				2,
				3,
				4,
				5,
				2,
				3,
				4,
				5
			]
		},
		{
			"type": "drum",
			"octaveScrollBar": 0,
			"instruments": [
				{
					"type": "noise",
					"volume": 100,
					"wave": "white",
					"transition": "smooth"
				}
			],
			"patterns": [
				{
					"instrument": 1,
					"notes": [
						{
							"pitches": [
								11
							],
							"points": [
								{
									"tick": 16,
									"pitchBend": 0,
									"volume": 100
								},
								{
									"tick": 22,
									"pitchBend": 0,
									"volume": 0
								},
								{
									"tick": 24,
									"pitchBend": 0,
									"volume": 0
								}
							]
						},
						{
							"pitches": [
								11
							],
							"points": [
								{
									"tick": 24,
									"pitchBend": 0,
									"volume": 100
								},
								{
									"tick": 29,
									"pitchBend": 0,
									"volume": 0
								},
								{
									"tick": 30,
									"pitchBend": 0,
									"volume": 0
								}
							]
						},
						{
							"pitches": [
								11
							],
							"points": [
								{
									"tick": 30,
									"pitchBend": 0,
									"volume": 100
								},
								{
									"tick": 32,
									"pitchBend": 0,
									"volume": 0
								}
							]
						},
						{
							"pitches": [
								11
							],
							"points": [
								{
									"tick": 32,
									"pitchBend": 0,
									"volume": 100
								},
								{
									"tick": 35,
									"pitchBend": 0,
									"volume": 0
								},
								{
									"tick": 36,
									"pitchBend": 0,
									"volume": 0
								}
							]
						},
						{
							"pitches": [
								11
							],
							"points": [
								{
									"tick": 36,
									"pitchBend": 0,
									"volume": 100
								},
								{
									"tick": 39,
									"pitchBend": 0,
									"volume": 0
								},
								{
									"tick": 40,
									"pitchBend": 0,
									"volume": 0
								}
							]
						},
						{
							"pitches": [
								11
							],
							"points": [
								{
									"tick": 40,
									"pitchBend": 0,
									"volume": 100
								},
								{
									"tick": 46,
									"pitchBend": 0,
									"volume": 0
								},
								{
									"tick": 48,
									"pitchBend": 0,
									"volume": 0
								}
							]
						},
						{
							"pitches": [
								11
							],
							"points": [
								{
									"tick": 48,
									"pitchBend": 0,
									"volume": 100
								},
								{
									"tick": 54,
									"pitchBend": 0,
									"volume": 0
								},
								{
									"tick": 56,
									"pitchBend": 0,
									"volume": 0
								}
							]
						},
						{
							"pitches": [
								11
							],
							"points": [
								{
									"tick": 56,
									"pitchBend": 0,
									"volume": 100
								},
								{
									"tick": 59,
									"pitchBend": 0,
									"volume": 0
								},
								{
									"tick": 60,
									"pitchBend": 0,
									"volume": 0
								}
							]
						},
						{
							"pitches": [
								11
							],
							"points": [
								{
									"tick": 60,
									"pitchBend": 0,
									"volume": 100
								},
								{
									"tick": 63,
									"pitchBend": 0,
									"volume": 0
								},
								{
									"tick": 64,
									"pitchBend": 0,
									"volume": 0
								}
							]
						},
						{
							"pitches": [
								11
							],
							"points": [
								{
									"tick": 64,
									"pitchBend": 0,
									"volume": 100
								},
								{
									"tick": 70,
									"pitchBend": 0,
									"volume": 0
								},
								{
									"tick": 72,
									"pitchBend": 0,
									"volume": 0
								}
							]
						},
						{
							"pitches": [
								11
							],
							"points": [
								{
									"tick": 72,
									"pitchBend": 0,
									"volume": 100
								},
								{
									"tick": 78,
									"pitchBend": 0,
									"volume": 0
								},
								{
									"tick": 80,
									"pitchBend": 0,
									"volume": 0
								}
							]
						},
						{
							"pitches": [
								11
							],
							"points": [
								{
									"tick": 80,
									"pitchBend": 0,
									"volume": 100
								},
								{
									"tick": 85,
									"pitchBend": 0,
									"volume": 0
								},
								{
									"tick": 86,
									"pitchBend": 0,
									"volume": 0
								}
							]
						},
						{
							"pitches": [
								11
							],
							"points": [
								{
									"tick": 86,
									"pitchBend": 0,
									"volume": 100
								},
								{
									"tick": 88,
									"pitchBend": 0,
									"volume": 0
								}
							]
						},
						{
							"pitches": [
								11
							],
							"points": [
								{
									"tick": 88,
									"pitchBend": 0,
									"volume": 100
								},
								{
									"tick": 91,
									"pitchBend": 0,
									"volume": 0
								},
								{
									"tick": 92,
									"pitchBend": 0,
									"volume": 0
								}
							]
						},
						{
							"pitches": [
								11
							],
							"points": [
								{
									"tick": 92,
									"pitchBend": 0,
									"volume": 100
								},
								{
									"tick": 95,
									"pitchBend": 0,
									"volume": 0
								},
								{
									"tick": 96,
									"pitchBend": 0,
									"volume": 0
								}
							]
						}
					]
				},
				{
					"instrument": 1,
					"notes": [
						{
							"pitches": [
								11
							],
							"points": [
								{
									"tick": 0,
									"pitchBend": 0,
									"volume": 100
								},
								{
									"tick": 6,
									"pitchBend": 0,
									"volume": 0
								},
								{
									"tick": 8,
									"pitchBend": 0,
									"volume": 0
								}
							]
						},
						{
							"pitches": [
								11
							],
							"points": [
								{
									"tick": 8,
									"pitchBend": 0,
									"volume": 100
								},
								{
									"tick": 14,
									"pitchBend": 0,
									"volume": 0
								},
								{
									"tick": 16,
									"pitchBend": 0,
									"volume": 0
								}
							]
						},
						{
							"pitches": [
								11
							],
							"points": [
								{
									"tick": 16,
									"pitchBend": 0,
									"volume": 100
								},
								{
									"tick": 22,
									"pitchBend": 0,
									"volume": 0
								}
							]
						},
						{
							"pitches": [
								11
							],
							"points": [
								{
									"tick": 22,
									"pitchBend": 0,
									"volume": 100
								},
								{
									"tick": 24,
									"pitchBend": 0,
									"volume": 0
								}
							]
						},
						{
							"pitches": [
								11
							],
							"points": [
								{
									"tick": 24,
									"pitchBend": 0,
									"volume": 100
								},
								{
									"tick": 28,
									"pitchBend": 0,
									"volume": 0
								}
							]
						},
						{
							"pitches": [
								11
							],
							"points": [
								{
									"tick": 28,
									"pitchBend": 0,
									"volume": 100
								},
								{
									"tick": 32,
									"pitchBend": 0,
									"volume": 0
								}
							]
						},
						{
							"pitches": [
								11
							],
							"points": [
								{
									"tick": 32,
									"pitchBend": 0,
									"volume": 100
								},
								{
									"tick": 40,
									"pitchBend": 0,
									"volume": 0
								}
							]
						},
						{
							"pitches": [
								11
							],
							"points": [
								{
									"tick": 40,
									"pitchBend": 0,
									"volume": 100
								},
								{
									"tick": 48,
									"pitchBend": 0,
									"volume": 0
								}
							]
						},
						{
							"pitches": [
								11
							],
							"points": [
								{
									"tick": 48,
									"pitchBend": 0,
									"volume": 100
								},
								{
									"tick": 54,
									"pitchBend": 0,
									"volume": 0
								}
							]
						},
						{
							"pitches": [
								11
							],
							"points": [
								{
									"tick": 54,
									"pitchBend": 0,
									"volume": 100
								},
								{
									"tick": 56,
									"pitchBend": 0,
									"volume": 0
								}
							]
						},
						{
							"pitches": [
								11
							],
							"points": [
								{
									"tick": 56,
									"pitchBend": 0,
									"volume": 100
								},
								{
									"tick": 60,
									"pitchBend": 0,
									"volume": 0
								}
							]
						},
						{
							"pitches": [
								11
							],
							"points": [
								{
									"tick": 60,
									"pitchBend": 0,
									"volume": 100
								},
								{
									"tick": 64,
									"pitchBend": 0,
									"volume": 0
								}
							]
						},
						{
							"pitches": [
								11
							],
							"points": [
								{
									"tick": 64,
									"pitchBend": 0,
									"volume": 100
								},
								{
									"tick": 72,
									"pitchBend": 0,
									"volume": 0
								}
							]
						},
						{
							"pitches": [
								11
							],
							"points": [
								{
									"tick": 72,
									"pitchBend": 0,
									"volume": 100
								},
								{
									"tick": 80,
									"pitchBend": 0,
									"volume": 0
								}
							]
						},
						{
							"pitches": [
								11
							],
							"points": [
								{
									"tick": 80,
									"pitchBend": 0,
									"volume": 100
								},
								{
									"tick": 86,
									"pitchBend": 0,
									"volume": 0
								}
							]
						},
						{
							"pitches": [
								11
							],
							"points": [
								{
									"tick": 86,
									"pitchBend": 0,
									"volume": 100
								},
								{
									"tick": 88,
									"pitchBend": 0,
									"volume": 0
								}
							]
						},
						{
							"pitches": [
								11
							],
							"points": [
								{
									"tick": 88,
									"pitchBend": 0,
									"volume": 100
								},
								{
									"tick": 92,
									"pitchBend": 0,
									"volume": 0
								}
							]
						},
						{
							"pitches": [
								11
							],
							"points": [
								{
									"tick": 92,
									"pitchBend": 0,
									"volume": 100
								},
								{
									"tick": 96,
									"pitchBend": 0,
									"volume": 0
								}
							]
						}
					]
				},
				{
					"instrument": 1,
					"notes": []
				},
				{
					"instrument": 1,
					"notes": []
				},
				{
					"instrument": 1,
					"notes": []
				},
				{
					"instrument": 1,
					"notes": []
				},
				{
					"instrument": 1,
					"notes": []
				},
				{
					"instrument": 1,
					"notes": []
				}
			],
			"sequence": [
				1,
				2,
				2,
				2,
				2,
				2,
				2,
				2,
				2,
				2,
				2,
				2,
				2,
				2,
				2,
				2,
				2,
				2,
				2,
				2,
				2,
				2,
				2,
				2,
				2,
				2,
				2,
				2,
				2,
				2,
				2,
				2
			]
		},
		{
			"type": "drum",
			"octaveScrollBar": 0,
			"instruments": [
				{
					"type": "noise",
					"volume": 100,
					"wave": "white",
					"transition": "sudden"
				}
			],
			"patterns": [
				{
					"instrument": 1,
					"notes": [
						{
							"pitches": [
								1
							],
							"points": [
								{
									"tick": 16,
									"pitchBend": 0,
									"volume": 100
								},
								{
									"tick": 24,
									"pitchBend": 0,
									"volume": 0
								}
							]
						},
						{
							"pitches": [
								1
							],
							"points": [
								{
									"tick": 24,
									"pitchBend": 0,
									"volume": 100
								},
								{
									"tick": 32,
									"pitchBend": 0,
									"volume": 0
								}
							]
						},
						{
							"pitches": [
								1
							],
							"points": [
								{
									"tick": 32,
									"pitchBend": 0,
									"volume": 100
								},
								{
									"tick": 40,
									"pitchBend": 0,
									"volume": 0
								}
							]
						},
						{
							"pitches": [
								1
							],
							"points": [
								{
									"tick": 40,
									"pitchBend": 0,
									"volume": 100
								},
								{
									"tick": 48,
									"pitchBend": 0,
									"volume": 0
								}
							]
						},
						{
							"pitches": [
								1
							],
							"points": [
								{
									"tick": 48,
									"pitchBend": 0,
									"volume": 100
								},
								{
									"tick": 56,
									"pitchBend": 0,
									"volume": 0
								}
							]
						},
						{
							"pitches": [
								1
							],
							"points": [
								{
									"tick": 56,
									"pitchBend": 0,
									"volume": 100
								},
								{
									"tick": 64,
									"pitchBend": 0,
									"volume": 0
								}
							]
						},
						{
							"pitches": [
								1
							],
							"points": [
								{
									"tick": 64,
									"pitchBend": 0,
									"volume": 100
								},
								{
									"tick": 72,
									"pitchBend": 0,
									"volume": 0
								}
							]
						},
						{
							"pitches": [
								1
							],
							"points": [
								{
									"tick": 72,
									"pitchBend": 0,
									"volume": 100
								},
								{
									"tick": 80,
									"pitchBend": 0,
									"volume": 0
								}
							]
						},
						{
							"pitches": [
								1
							],
							"points": [
								{
									"tick": 80,
									"pitchBend": 0,
									"volume": 100
								},
								{
									"tick": 88,
									"pitchBend": 0,
									"volume": 0
								}
							]
						},
						{
							"pitches": [
								1
							],
							"points": [
								{
									"tick": 88,
									"pitchBend": 0,
									"volume": 100
								},
								{
									"tick": 96,
									"pitchBend": 0,
									"volume": 0
								}
							]
						}
					]
				},
				{
					"instrument": 1,
					"notes": [
						{
							"pitches": [
								1
							],
							"points": [
								{
									"tick": 0,
									"pitchBend": 0,
									"volume": 100
								},
								{
									"tick": 8,
									"pitchBend": 0,
									"volume": 0
								}
							]
						},
						{
							"pitches": [
								1
							],
							"points": [
								{
									"tick": 8,
									"pitchBend": 0,
									"volume": 100
								},
								{
									"tick": 16,
									"pitchBend": 0,
									"volume": 0
								}
							]
						},
						{
							"pitches": [
								1
							],
							"points": [
								{
									"tick": 16,
									"pitchBend": 0,
									"volume": 100
								},
								{
									"tick": 24,
									"pitchBend": 0,
									"volume": 0
								}
							]
						},
						{
							"pitches": [
								1
							],
							"points": [
								{
									"tick": 24,
									"pitchBend": 0,
									"volume": 100
								},
								{
									"tick": 32,
									"pitchBend": 0,
									"volume": 0
								}
							]
						},
						{
							"pitches": [
								1
							],
							"points": [
								{
									"tick": 32,
									"pitchBend": 0,
									"volume": 100
								},
								{
									"tick": 40,
									"pitchBend": 0,
									"volume": 0
								}
							]
						},
						{
							"pitches": [
								1
							],
							"points": [
								{
									"tick": 40,
									"pitchBend": 0,
									"volume": 100
								},
								{
									"tick": 48,
									"pitchBend": 0,
									"volume": 0
								}
							]
						},
						{
							"pitches": [
								1
							],
							"points": [
								{
									"tick": 48,
									"pitchBend": 0,
									"volume": 100
								},
								{
									"tick": 56,
									"pitchBend": 0,
									"volume": 0
								}
							]
						},
						{
							"pitches": [
								1
							],
							"points": [
								{
									"tick": 56,
									"pitchBend": 0,
									"volume": 100
								},
								{
									"tick": 64,
									"pitchBend": 0,
									"volume": 0
								}
							]
						},
						{
							"pitches": [
								1
							],
							"points": [
								{
									"tick": 64,
									"pitchBend": 0,
									"volume": 100
								},
								{
									"tick": 72,
									"pitchBend": 0,
									"volume": 0
								}
							]
						},
						{
							"pitches": [
								1
							],
							"points": [
								{
									"tick": 72,
									"pitchBend": 0,
									"volume": 100
								},
								{
									"tick": 80,
									"pitchBend": 0,
									"volume": 0
								}
							]
						},
						{
							"pitches": [
								1
							],
							"points": [
								{
									"tick": 80,
									"pitchBend": 0,
									"volume": 100
								},
								{
									"tick": 88,
									"pitchBend": 0,
									"volume": 0
								}
							]
						},
						{
							"pitches": [
								1
							],
							"points": [
								{
									"tick": 88,
									"pitchBend": 0,
									"volume": 100
								},
								{
									"tick": 96,
									"pitchBend": 0,
									"volume": 0
								}
							]
						}
					]
				},
				{
					"instrument": 1,
					"notes": []
				},
				{
					"instrument": 1,
					"notes": []
				},
				{
					"instrument": 1,
					"notes": []
				},
				{
					"instrument": 1,
					"notes": []
				},
				{
					"instrument": 1,
					"notes": []
				},
				{
					"instrument": 1,
					"notes": []
				}
			],
			"sequence": [
				1,
				2,
				2,
				2,
				2,
				2,
				2,
				2,
				2,
				2,
				2,
				2,
				2,
				2,
				2,
				2,
				2,
				2,
				2,
				2,
				2,
				2,
				2,
				2,
				2,
				2,
				2,
				2,
				2,
				2,
				2,
				2
			]
		}
	]
}